shira/__init__.py
shira/audio_search.py
shira/cli.py
shira/utils.py
shira_audio-0.1.292.dist-info/METADATA
shira_audio-0.1.292.dist-info/WHEEL
shira_audio-0.1.292.dist-info/entry_points.txt
shira_audio-0.1.292.dist-info/licenses/LICENSE
shira_audio-0.1.292.dist-info/RECORD
