Metadata-Version: 2.3
Name: shira_audio
Version: 0.1.292
Summary: audio search/retrieval library
Project-URL: Homepage, https://pypi.org/project/shira_audio/
Project-URL: Repository, https://github.com/kelechi-c/shira_audio
Author-email: Chibuzo Kelechi <kelechichibuzo7@gmail.com>
License: Apache License
License-File: LICENSE
Keywords: audio retrieval,machine learning,multimodal,semantic search,vector/neural embeddings
Requires-Python: >=3.9
Requires-Dist: click
Requires-Dist: datasets
Requires-Dist: faiss-cpu
Requires-Dist: faiss-gpu
Requires-Dist: librosa
Requires-Dist: numpy
Requires-Dist: soundfile>=0.12.1
Requires-Dist: tqdm
Requires-Dist: transformers
